pyopenalsoft/__init__.py
pyopenalsoft/py.typed
pyopenalsoft/pyopenalsoft.pyd
pyopenalsoft/pyopenalsoft.pyi
pyopenalsoft/Win32/soft_oal.dll
pyopenalsoft/Win64/soft_oal.dll
pyopenalsoft-1.0.0.dist-info/METADATA
pyopenalsoft-1.0.0.dist-info/WHEEL
pyopenalsoft-1.0.0.dist-info/top_level.txt
pyopenalsoft-1.0.0.dist-info/RECORD
