Metadata-Version: 2.4
Name: pyopenalsoft
Version: 1.0.0
Author: hashkth
Requires-Python: <3.14,>=3.11
